CHANGELOG.txt
LICENCE.txt
MANIFEST.in
README.txt
setup.py
CEEcache/__init__.py
CEEcache/logger.py
CEEcache.egg-info/PKG-INFO
CEEcache.egg-info/SOURCES.txt
CEEcache.egg-info/dependency_links.txt
CEEcache.egg-info/requires.txt
CEEcache.egg-info/top_level.txt