Metadata-Version: 2.1
Name: CEEcache
Version: 1.0.3
Summary: Caching the JSON request payload and the value in RedisQ
Home-page: UNKNOWN
Author: Netcore Cloud
Author-email: aditya.singh@netcorecloud.com
License: MIT
Platform: UNKNOWN
Classifier: Operating System :: OS Independent
Classifier: License :: OSI Approved :: MIT License
Classifier: Programming Language :: Python :: 3
License-File: LICENCE.txt
